mrtutils/__init__.py
mrtutils/device.py
mrtutils/gatt_profile.py
mrtutils/kconfig
mrtutils/menuconfig.py
mrtutils/modsync.py
mrtutils/mrt
mrtutils/mrtDocHelper.py
mrtutils/mrtTemplateHelper.py
mrtutils/mrtYamlHelper.py
mrtutils/mrt_ble.py
mrtutils/mrt_config.py
mrtutils/mrt_config_gui.py
mrtutils/mrt_device.py
mrtutils/mrt_doc.py
mrtutils/mrt_gen.py
mrtutils/mrt_version.py
mrtutils/updates.py
mrtutils/sphinx/__init__.py
mrtutils/sphinx/register.py
mrtutils/templates/ble/app_service_source.c
mrtutils/templates/ble/gatt_descriptor_template.yml
mrtutils/templates/ble/gatt_icd.html
mrtutils/templates/ble/gatt_icd.rst
mrtutils/templates/ble/nrf_definitions.json
mrtutils/templates/ble/profile_header.h
mrtutils/templates/ble/profile_source.c
mrtutils/templates/ble/service_header.h
mrtutils/templates/ble/service_source.c
mrtutils/templates/ble/smart_icd.html
mrtutils/templates/ble/esp32/CMakeLists.txt
mrtutils/templates/ble/esp32/component.mk
mrtutils/templates/ble/esp32/gatt_server.c
mrtutils/templates/ble/esp32/gatt_server.h
mrtutils/templates/ble/esp32/kconfig
mrtutils/templates/device/device_descriptor_template.yml
mrtutils/templates/device/device_doc.md
mrtutils/templates/device/device_doc.rst
mrtutils/templates/device/device_header_template.h
mrtutils/templates/device/device_regmap.html
mrtutils/templates/device/device_regs_header.h
mrtutils/templates/device/device_slave_header.h
mrtutils/templates/device/device_slave_source.c
mrtutils/templates/device/device_source_template.c
mrtutils/templates/doc/Makefile
mrtutils/templates/doc/README.rst
mrtutils/templates/doc/conf.py
mrtutils/templates/doc/index.rst
mrtutils/templates/doc/layout.html
mrtutils/templates/doc/moddoc_index.rst
mrtutils/templates/doc/assets/diagrams/button.puml
mrtutils/templates/doc/assets/diagrams/led.puml
mrtutils/templates/doc/assets/diagrams/mockup.dio.png
mrtutils/templates/doc/assets/diagrams/system.dio.png
mrtutils/templates/doc/assets/images/favicon.ico
mrtutils-0.3.39.dist-info/METADATA
mrtutils-0.3.39.dist-info/WHEEL
mrtutils-0.3.39.dist-info/entry_points.txt
mrtutils-0.3.39.dist-info/licenses/LICENSE
mrtutils-0.3.39.dist-info/RECORD
