Metadata-Version: 2.4
Name: mrtutils
Version: 0.3.39
Summary: Utilities for MrT
Project-URL: homepage, https://mrt.readthedocs.io/en/latest/index.html
Project-URL: repository, https://mrt.readthedocs.io/en/latest/index.html
Author-email: Jason Berger <Berge472@gmail.com>
License: MIT
License-File: LICENSE
Requires-Python: >=3.7
Requires-Dist: gitpython
Requires-Dist: kconfiglib
Requires-Dist: mako
Requires-Dist: markdown
Requires-Dist: polypacket
Requires-Dist: pyyaml
Requires-Dist: update-notipy
Provides-Extra: dev
Requires-Dist: pytest>=7.0.0; extra == 'dev'
Requires-Dist: sphinx>=4.0.0; extra == 'dev'
